truegrad/__init__.py
truegrad/functional.py
truegrad/optim.py
truegrad/test.py
truegrad/utils.py
truegrad/nn/__init__.py
truegrad/nn/functional.py
truegrad-5.0.0.dist-info/LICENSE
truegrad-5.0.0.dist-info/METADATA
truegrad-5.0.0.dist-info/WHEEL
truegrad-5.0.0.dist-info/top_level.txt
truegrad-5.0.0.dist-info/RECORD
