Metadata-Version: 2.1
Name: truegrad
Version: 5.0.0
Summary: PyTorch interface for TrueGrad-AdamW
Home-page: https://github.com/clashluke/truegrad
Author: Lucas Nestler
Author-email: github.truegrad@nestler.sh
License: BSD
Classifier: Development Status :: 5 - Production/Stable
Classifier: License :: OSI Approved :: BSD License
Classifier: Programming Language :: Python
Classifier: Programming Language :: Python :: 3.7
Classifier: Programming Language :: Python :: 3.8
Classifier: Programming Language :: Python :: 3.9
Classifier: Programming Language :: Python :: 3.10
Classifier: Topic :: Software Development :: Libraries
Classifier: Topic :: Software Development :: Libraries :: Python Modules
Classifier: Intended Audience :: Developers
Requires-Python: >=3.7
License-File: LICENSE
